pydeflate/.pydeflate_data/README.md
pydeflate/__init__.py
pydeflate/cache.py
pydeflate/constants.py
pydeflate/context.py
pydeflate/core/__init__.py
pydeflate/core/api.py
pydeflate/core/deflator.py
pydeflate/core/exchange.py
pydeflate/core/source.py
pydeflate/deflate/__init__.py
pydeflate/deflate/deflators.py
pydeflate/deflate/get_deflators.py
pydeflate/deflate/legacy_deflate.py
pydeflate/exceptions.py
pydeflate/exchange/__init__.py
pydeflate/exchange/exchangers.py
pydeflate/exchange/get_rates.py
pydeflate/plugins.py
pydeflate/protocols.py
pydeflate/pydeflate_config.py
pydeflate/schemas.py
pydeflate/settings/emu.json
pydeflate/settings/oecd_codes.json
pydeflate/sources/__init__.py
pydeflate/sources/common.py
pydeflate/sources/dac.py
pydeflate/sources/imf.py
pydeflate/sources/world_bank.py
pydeflate/utils.py
pydeflate-2.3.3.dist-info/licenses/LICENSE
pydeflate-2.3.3.dist-info/WHEEL
pydeflate-2.3.3.dist-info/METADATA
pydeflate-2.3.3.dist-info/RECORD
