Metadata-Version: 2.4
Name: pydeflate
Version: 2.3.3
Summary: Package to convert current prices figures to constant prices and vice versa
Author: Jorge Rivera
Author-email: Jorge Rivera <Jorge.Rivera@one.org>
License-Expression: MIT
License-File: LICENSE
Requires-Dist: hdx-python-country>=3.9.8
Requires-Dist: imf-reader>=1.4.1
Requires-Dist: oda-reader>=1.3.0
Requires-Dist: pandas>=2.0
Requires-Dist: pandera>=0.20.0
Requires-Dist: pyarrow>=14.0
Requires-Dist: requests>=2.32.5
Requires-Dist: wbgapi>=1.0.12
Requires-Dist: platformdirs>=3.0.0
Requires-Dist: filelock>=3.15.0
Maintainer: Jorge Rivera
Requires-Python: >=3.11
Project-URL: Homepage, https://github.com/jm-rivera/pydeflate
Project-URL: Issues, https://github.com/jm-rivera/pydeflate/issues
Project-URL: Repository, https://github.com/jm-rivera/pydeflate
